{"quote_count": 0, "quoted_status_permalink": {"url": "https://t.co/57KdUZZ4Sz", "expanded": "https://twitter.com/eplbible/status/1133756746512719872", "display": "twitter.com/eplbible/statu\u2026"}, "contributors": null, "truncated": false, "text": "Still rate the Arsenal 2003/4 team &amp; Chelsea 2004/5 team higher than this ManCity team.", "is_quote_status": true, "in_reply_to_status_id": null, "reply_count": 0, "id": 1134105500474327041, "favorite_count": 0, "entities": {"user_mentions": [], "symbols": [], "hashtags": [], "urls": []}, "quoted_status_id": 1133756746512719872, "retweeted": false, "coordinates": null, "timestamp_ms": "1559226796631", "quoted_status": {"quote_count": 202, "contributors": null, "truncated": true, "text": "FourFourTwo's list of best ever Premier League teams:\n\n1. Man City 2017/18\n2. Arsenal 2003/04\n3. Man City 2018/19\n4\u2026 https://t.co/K5Q2XUzKPu", "is_quote_status": false, "in_reply_to_status_id": null, "reply_count": 314, "id": 1133756746512719872, "favorite_count": 1684, "entities": {"user_mentions": [], "symbols": [], "hashtags": [], "urls": [{"url": "https://t.co/K5Q2XUzKPu", "indices": [117, 140], "expanded_url": "https://twitter.com/i/web/status/1133756746512719872", "display_url": "twitter.com/i/web/status/1\u2026"}]}, "retweeted": false, "coordinates": null, "source": "<a href=\"http://twitter.com/download/iphone\" rel=\"nofollow\">Twitter for iPhone</a>", "in_reply_to_screen_name": null, "id_str": "1133756746512719872", "retweet_count": 280, "in_reply_to_user_id": null, "favorited": false, "user": {"follow_request_sent": null, "profile_use_background_image": true, "default_profile_image": false, "id": 595343731, "default_profile": false, "verified": false, "profile_image_url_https": "https://pbs.twimg.com/profile_images/1113389264493060096/21WzgGGX_normal.jpg", "profile_sidebar_fill_color": "DDEEF6", "profile_text_color": "333333", "followers_count": 617293, "profile_sidebar_border_color": "FFFFFF", "id_str": "595343731", "profile_background_color": "EDECE9", "listed_count": 2718, "profile_background_image_url_https": "https://abs.twimg.com/images/themes/theme3/bg.gif", "utc_offset": null, "statuses_count": 17477, "description": "Your #1 source for everything Premier League related. 18+.", "friends_count": 270, "location": "Barclaysbible@gmail.com", "profile_link_color": "3B94D9", "profile_image_url": "http://pbs.twimg.com/profile_images/1113389264493060096/21WzgGGX_normal.jpg", "following": null, "geo_enabled": true, "profile_banner_url": "https://pbs.twimg.com/profile_banners/595343731/1554327600", "profile_background_image_url": "http://abs.twimg.com/images/themes/theme3/bg.gif", "name": "Transfer News", "lang": null, "profile_background_tile": true, "favourites_count": 4, "screen_name": "EPLBible", "notifications": null, "url": null, "created_at": "Thu May 31 09:35:07 +0000 2012", "contributors_enabled": false, "time_zone": null, "protected": false, "translator_type": "none", "is_translator": false}, "geo": null, "in_reply_to_user_id_str": null, "lang": "en", "extended_tweet": {"display_text_range": [0, 185], "entities": {"user_mentions": [], "symbols": [], "hashtags": [], "urls": []}, "full_text": "FourFourTwo's list of best ever Premier League teams:\n\n1. Man City 2017/18\n2. Arsenal 2003/04\n3. Man City 2018/19\n4. Liverpool 2018/19\n5. Chelsea 2004/05\n6. Chelsea 2016/17\n\nThoughts? \ud83e\udd14"}, "created_at": "Wed May 29 15:27:27 +0000 2019", "filter_level": "low", "in_reply_to_status_id_str": null, "place": null}, "source": "<a href=\"http://twitter.com/download/iphone\" rel=\"nofollow\">Twitter for iPhone</a>", "in_reply_to_screen_name": null, "id_str": "1134105500474327041", "retweet_count": 0, "in_reply_to_user_id": null, "favorited": false, "user": {"follow_request_sent": null, "profile_use_background_image": true, "default_profile_image": false, "id": 65859751, "default_profile": false, "verified": false, "profile_image_url_https": "https://pbs.twimg.com/profile_images/951915067464912896/6Tc12Orp_normal.jpg", "profile_sidebar_fill_color": "DDEEF6", "profile_text_color": "333333", "followers_count": 2078, "profile_sidebar_border_color": "000000", "id_str": "65859751", "profile_background_color": "C0DEED", "listed_count": 54, "profile_background_image_url_https": "https://abs.twimg.com/images/themes/theme1/bg.png", "utc_offset": null, "statuses_count": 138490, "description": "Ambivert with dire love for music, football and data. No man's knowledge here can go beyond his experience.", "friends_count": 863, "location": "kampala,uganda", "profile_link_color": "0084B4", "profile_image_url": "http://pbs.twimg.com/profile_images/951915067464912896/6Tc12Orp_normal.jpg", "following": null, "geo_enabled": true, "profile_banner_url": "https://pbs.twimg.com/profile_banners/65859751/1545216155", "profile_background_image_url": "http://abs.twimg.com/images/themes/theme1/bg.png", "name": "NANGOSYAHTOMWELLARD", "lang": null, "profile_background_tile": true, "favourites_count": 4514, "screen_name": "thatbadGISHUboy", "notifications": null, "url": "http://nangosyahtom.wordpress.com", "created_at": "Sat Aug 15 08:24:09 +0000 2009", "contributors_enabled": false, "time_zone": null, "protected": false, "translator_type": "none", "is_translator": false}, "geo": null, "in_reply_to_user_id_str": null, "lang": "en", "created_at": "Thu May 30 14:33:16 +0000 2019", "quoted_status_id_str": "1133756746512719872", "filter_level": "low", "in_reply_to_status_id_str": null, "place": {"full_name": "Kampala, Uganda", "url": "https://api.twitter.com/1.1/geo/id/000c69ad123213a8.json", "country": "Uganda", "place_type": "admin", "bounding_box": {"type": "Polygon", "coordinates": [[[32.416623, 0.164853], [32.416623, 0.413682], [32.721697, 0.413682], [32.721697, 0.164853]]]}, "country_code": "UG", "attributes": {}, "id": "000c69ad123213a8", "name": "Kampala"}}
{"quote_count": 0, "contributors": null, "truncated": true, "text": "@YRyobara @hodjs @CastleLiteUg @johnniewalkerug @MalembeLife @PepsiUganda @mtnug @nxtradioug @lagumtherapper\u2026 https://t.co/HK7qPdBoTj", "is_quote_status": false, "in_reply_to_status_id": 1134104976542883842, "reply_count": 0, "id": 1134105510955892738, "favorite_count": 0, "entities": {"user_mentions": [{"id": 928899905501921281, "indices": [0, 9], "id_str": "928899905501921281", "screen_name": "YRyobara", "name": "Yubs"}, {"id": 293416972, "indices": [10, 16], "id_str": "293416972", "screen_name": "hodjs", "name": "House Of DJs"}, {"id": 1578498290, "indices": [17, 30], "id_str": "1578498290", "screen_name": "CastleLiteUg", "name": "Castle Lite Uganda"}, {"id": 778235841055522817, "indices": [31, 47], "id_str": "778235841055522817", "screen_name": "johnniewalkerug", "name": "Johnnie Walker UG"}, {"id": 441753461, "indices": [48, 60], "id_str": "441753461", "screen_name": "MalembeLife", "name": "MALEMBE LIFESTYLE"}, {"id": 953416652, "indices": [61, 73], "id_str": "953416652", "screen_name": "PepsiUganda", "name": "Pepsi Uganda"}, {"id": 238115057, "indices": [74, 80], "id_str": "238115057", "screen_name": "mtnug", "name": "MTN Uganda"}, {"id": 935560333124661248, "indices": [81, 92], "id_str": "935560333124661248", "screen_name": "nxtradioug", "name": "Nxt Radio"}, {"id": 734532577, "indices": [93, 108], "id_str": "734532577", "screen_name": "lagumtherapper", "name": "lagum"}], "symbols": [], "hashtags": [], "urls": [{"url": "https://t.co/HK7qPdBoTj", "indices": [110, 133], "expanded_url": "https://twitter.com/i/web/status/1134105510955892738", "display_url": "twitter.com/i/web/status/1\u2026"}]}, "retweeted": false, "coordinates": null, "timestamp_ms": "1559226799130", "source": "<a href=\"http://twitter.com/download/iphone\" rel=\"nofollow\">Twitter for iPhone</a>", "in_reply_to_screen_name": "YRyobara", "id_str": "1134105510955892738", "display_text_range": [117, 140], "retweet_count": 0, "in_reply_to_user_id": 928899905501921281, "favorited": false, "user": {"follow_request_sent": null, "profile_use_background_image": true, "default_profile_image": false, "id": 18184674, "default_profile": false, "verified": true, "profile_image_url_https": "https://pbs.twimg.com/profile_images/1127937541901037570/jPoEXVWx_normal.jpg", "profile_sidebar_fill_color": "EFEFEF", "profile_text_color": "333333", "followers_count": 36453, "profile_sidebar_border_color": "000000", "id_str": "18184674", "profile_background_color": "131516", "listed_count": 83, "profile_background_image_url_https": "https://abs.twimg.com/images/themes/theme14/bg.gif", "utc_offset": null, "statuses_count": 18443, "description": "Socks Salesman - @DapperByDenzelUG | Radio - @XfmUG | Tv - @UrbanTvUganda | Columnist - @NewVisionwire | #BTS fan | Denzel.UG@gmail.com +256791957439", "friends_count": 4798, "location": "Kampala, Uganda", "profile_link_color": "3B94D9", "profile_image_url": "http://pbs.twimg.com/profile_images/1127937541901037570/jPoEXVWx_normal.jpg", "following": null, "geo_enabled": true, "profile_banner_url": "https://pbs.twimg.com/profile_banners/18184674/1556102413", "profile_background_image_url": "http://abs.twimg.com/images/themes/theme14/bg.gif", "name": "Charlie Denzel Mwiyeretsi \ud83c\uddfa\ud83c\uddec", "lang": null, "profile_background_tile": true, "favourites_count": 13210, "screen_name": "DenzelUG", "notifications": null, "url": "http://www.instagram.com/DenzelUG", "created_at": "Wed Dec 17 07:13:50 +0000 2008", "contributors_enabled": false, "time_zone": null, "protected": false, "translator_type": "none", "is_translator": false}, "geo": null, "in_reply_to_user_id_str": "928899905501921281", "lang": "en", "extended_tweet": {"display_text_range": [158, 210], "entities": {"user_mentions": [{"id": 928899905501921281, "indices": [0, 9], "id_str": "928899905501921281", "screen_name": "YRyobara", "name": "Yubs"}, {"id": 293416972, "indices": [10, 16], "id_str": "293416972", "screen_name": "hodjs", "name": "House Of DJs"}, {"id": 1578498290, "indices": [17, 30], "id_str": "1578498290", "screen_name": "CastleLiteUg", "name": "Castle Lite Uganda"}, {"id": 778235841055522817, "indices": [31, 47], "id_str": "778235841055522817", "screen_name": "johnniewalkerug", "name": "Johnnie Walker UG"}, {"id": 441753461, "indices": [48, 60], "id_str": "441753461", "screen_name": "MalembeLife", "name": "MALEMBE LIFESTYLE"}, {"id": 953416652, "indices": [61, 73], "id_str": "953416652", "screen_name": "PepsiUganda", "name": "Pepsi Uganda"}, {"id": 238115057, "indices": [74, 80], "id_str": "238115057", "screen_name": "mtnug", "name": "MTN Uganda"}, {"id": 935560333124661248, "indices": [81, 92], "id_str": "935560333124661248", "screen_name": "nxtradioug", "name": "Nxt Radio"}, {"id": 734532577, "indices": [93, 108], "id_str": "734532577", "screen_name": "lagumtherapper", "name": "lagum"}, {"id": 115644179, "indices": [109, 121], "id_str": "115644179", "screen_name": "KwestaDaKAR", "name": "\ud83d\udc8d#KhethileKhethile"}, {"id": 55474598, "indices": [122, 136], "id_str": "55474598", "screen_name": "SunELMusician", "name": "Sun-EL Musician"}, {"id": 235512729, "indices": [137, 150], "id_str": "235512729", "screen_name": "TheMithMusic", "name": "\ud83c\uddfa\ud83c\uddec\ud83c\uddfa\ud83c\uddec"}, {"id": 2679055230, "indices": [151, 157], "id_str": "2679055230", "screen_name": "TIDAL", "name": "TIDAL"}, {"id": 55474598, "indices": [168, 182], "id_str": "55474598", "screen_name": "SunELMusician", "name": "Sun-EL Musician"}], "symbols": [], "hashtags": [{"indices": [196, 210], "text": "TheLockDownUg"}], "urls": []}, "full_text": "@YRyobara @hodjs @CastleLiteUg @johnniewalkerug @MalembeLife @PepsiUganda @mtnug @nxtradioug @lagumtherapper @KwestaDaKAR @SunELMusician @TheMithMusic @TIDAL Nice! Hey @SunELMusician .. come see! #TheLockDownUg"}, "created_at": "Thu May 30 14:33:19 +0000 2019", "filter_level": "low", "in_reply_to_status_id_str": "1134104976542883842", "place": {"full_name": "Kampala, Uganda", "url": "https://api.twitter.com/1.1/geo/id/000c69ad123213a8.json", "country": "Uganda", "place_type": "admin", "bounding_box": {"type": "Polygon", "coordinates": [[[32.416623, 0.164853], [32.416623, 0.413682], [32.721697, 0.413682], [32.721697, 0.164853]]]}, "country_code": "UG", "attributes": {}, "id": "000c69ad123213a8", "name": "Kampala"}}
{"quote_count": 0, "contributors": null, "truncated": true, "text": "@SarahSolomong @hodjs @CastleLiteUg @johnniewalkerug @MalembeLife @PepsiUganda @mtnug @nxtradioug @lagumtherapper\u2026 https://t.co/kzD6KGfgIM", "is_quote_status": false, "in_reply_to_status_id": 1134084503461400576, "reply_count": 0, "id": 1134105629721812992, "favorite_count": 0, "entities": {"user_mentions": [{"id": 1062789286347583488, "indices": [0, 14], "id_str": "1062789286347583488", "screen_name": "SarahSolomong", "name": "Sarah Solomon (Queen Solomon)"}, {"id": 293416972, "indices": [15, 21], "id_str": "293416972", "screen_name": "hodjs", "name": "House Of DJs"}, {"id": 1578498290, "indices": [22, 35], "id_str": "1578498290", "screen_name": "CastleLiteUg", "name": "Castle Lite Uganda"}, {"id": 778235841055522817, "indices": [36, 52], "id_str": "778235841055522817", "screen_name": "johnniewalkerug", "name": "Johnnie Walker UG"}, {"id": 441753461, "indices": [53, 65], "id_str": "441753461", "screen_name": "MalembeLife", "name": "MALEMBE LIFESTYLE"}, {"id": 953416652, "indices": [66, 78], "id_str": "953416652", "screen_name": "PepsiUganda", "name": "Pepsi Uganda"}, {"id": 238115057, "indices": [79, 85], "id_str": "238115057", "screen_name": "mtnug", "name": "MTN Uganda"}, {"id": 935560333124661248, "indices": [86, 97], "id_str": "935560333124661248", "screen_name": "nxtradioug", "name": "Nxt Radio"}, {"id": 734532577, "indices": [98, 113], "id_str": "734532577", "screen_name": "lagumtherapper", "name": "lagum"}], "symbols": [], "hashtags": [], "urls": [{"url": "https://t.co/kzD6KGfgIM", "indices": [115, 138], "expanded_url": "https://twitter.com/i/web/status/1134105629721812992", "display_url": "twitter.com/i/web/status/1\u2026"}]}, "retweeted": false, "coordinates": null, "timestamp_ms": "1559226827446", "source": "<a href=\"http://twitter.com/download/iphone\" rel=\"nofollow\">Twitter for iPhone</a>", "in_reply_to_screen_name": "SarahSolomong", "id_str": "1134105629721812992", "display_text_range": [117, 140], "retweet_count": 0, "in_reply_to_user_id": 1062789286347583488, "favorited": false, "user": {"follow_request_sent": null, "profile_use_background_image": true, "default_profile_image": false, "id": 2470590086, "default_profile": true, "verified": false, "profile_image_url_https": "https://pbs.twimg.com/profile_images/1031981799726088197/Ny2cUBJS_normal.jpg", "profile_sidebar_fill_color": "DDEEF6", "profile_text_color": "333333", "followers_count": 2934, "profile_sidebar_border_color": "C0DEED", "id_str": "2470590086", "profile_background_color": "C0DEED", "listed_count": 27, "profile_background_image_url_https": "https://abs.twimg.com/images/themes/theme1/bg.png", "utc_offset": null, "statuses_count": 65559, "description": "Tribal/Deep House & Reggae lover : ______________________________________________For all your Moving Errands (Office, home, etc), kindly Dm.", "friends_count": 970, "location": "Kampala, Uganda", "profile_link_color": "1DA1F2", "profile_image_url": "http://pbs.twimg.com/profile_images/1031981799726088197/Ny2cUBJS_normal.jpg", "following": null, "geo_enabled": true, "profile_banner_url": "https://pbs.twimg.com/profile_banners/2470590086/1558723073", "profile_background_image_url": "http://abs.twimg.com/images/themes/theme1/bg.png", "name": "Mr. B\u00e1ldi\u00e9 R\u00e9nz\u00e9l", "lang": null, "profile_background_tile": false, "favourites_count": 37970, "screen_name": "Kamali_21", "notifications": null, "url": "http://www.quickerrands.com", "created_at": "Wed Apr 30 09:15:11 +0000 2014", "contributors_enabled": false, "time_zone": null, "protected": false, "translator_type": "none", "is_translator": false}, "geo": null, "in_reply_to_user_id_str": "1062789286347583488", "lang": "en", "extended_tweet": {"display_text_range": [156, 189], "entities": {"user_mentions": [{"id": 1062789286347583488, "indices": [0, 14], "id_str": "1062789286347583488", "screen_name": "SarahSolomong", "name": "Sarah Solomon (Queen Solomon)"}, {"id": 293416972, "indices": [15, 21], "id_str": "293416972", "screen_name": "hodjs", "name": "House Of DJs"}, {"id": 1578498290, "indices": [22, 35], "id_str": "1578498290", "screen_name": "CastleLiteUg", "name": "Castle Lite Uganda"}, {"id": 778235841055522817, "indices": [36, 52], "id_str": "778235841055522817", "screen_name": "johnniewalkerug", "name": "Johnnie Walker UG"}, {"id": 441753461, "indices": [53, 65], "id_str": "441753461", "screen_name": "MalembeLife", "name": "MALEMBE LIFESTYLE"}, {"id": 953416652, "indices": [66, 78], "id_str": "953416652", "screen_name": "PepsiUganda", "name": "Pepsi Uganda"}, {"id": 238115057, "indices": [79, 85], "id_str": "238115057", "screen_name": "mtnug", "name": "MTN Uganda"}, {"id": 935560333124661248, "indices": [86, 97], "id_str": "935560333124661248", "screen_name": "nxtradioug", "name": "Nxt Radio"}, {"id": 734532577, "indices": [98, 113], "id_str": "734532577", "screen_name": "lagumtherapper", "name": "lagum"}, {"id": 115644179, "indices": [114, 126], "id_str": "115644179", "screen_name": "KwestaDaKAR", "name": "\ud83d\udc8d#KhethileKhethile"}, {"id": 55474598, "indices": [127, 141], "id_str": "55474598", "screen_name": "SunELMusician", "name": "Sun-EL Musician"}, {"id": 235512729, "indices": [142, 155], "id_str": "235512729", "screen_name": "TheMithMusic", "name": "\ud83c\uddfa\ud83c\uddec\ud83c\uddfa\ud83c\uddec"}], "symbols": [], "hashtags": [], "urls": []}, "full_text": "@SarahSolomong @hodjs @CastleLiteUg @johnniewalkerug @MalembeLife @PepsiUganda @mtnug @nxtradioug @lagumtherapper @KwestaDaKAR @SunELMusician @TheMithMusic \"He doesn't have money\" I think \ud83d\ude1c"}, "created_at": "Thu May 30 14:33:47 +0000 2019", "filter_level": "low", "in_reply_to_status_id_str": "1134084503461400576", "place": {"full_name": "Wakiso, Uganda", "url": "https://api.twitter.com/1.1/geo/id/0092409a629e836c.json", "country": "Uganda", "place_type": "admin", "bounding_box": {"type": "Polygon", "coordinates": [[[32.192297, -0.147789], [32.192297, 0.585072], [32.683699, 0.585072], [32.683699, -0.147789]]]}, "country_code": "UG", "attributes": {}, "id": "0092409a629e836c", "name": "Wakiso"}}
{"quote_count": 0, "contributors": null, "truncated": true, "text": "@CarolNatukunda Ohh God!!\nThat's why they use HS codes. Tax collectors may not know all the products but they'll kn\u2026 https://t.co/QLUZtbxpzY", "is_quote_status": false, "in_reply_to_status_id": 1134104996881063938, "reply_count": 0, "id": 1134105640115290112, "favorite_count": 0, "entities": {"user_mentions": [{"id": 437573692, "indices": [0, 15], "id_str": "437573692", "screen_name": "CarolNatukunda", "name": "Carol Natukunda"}], "symbols": [], "hashtags": [], "urls": [{"url": "https://t.co/QLUZtbxpzY", "indices": [117, 140], "expanded_url": "https://twitter.com/i/web/status/1134105640115290112", "display_url": "twitter.com/i/web/status/1\u2026"}]}, "retweeted": false, "coordinates": null, "timestamp_ms": "1559226829924", "source": "<a href=\"http://twitter.com/download/android\" rel=\"nofollow\">Twitter for Android</a>", "in_reply_to_screen_name": "CarolNatukunda", "id_str": "1134105640115290112", "display_text_range": [16, 140], "retweet_count": 0, "in_reply_to_user_id": 437573692, "favorited": false, "user": {"follow_request_sent": null, "profile_use_background_image": false, "default_profile_image": false, "id": 725791584910888961, "default_profile": false, "verified": false, "profile_image_url_https": "https://pbs.twimg.com/profile_images/1031132166036631552/Yewxcyqo_normal.jpg", "profile_sidebar_fill_color": "000000", "profile_text_color": "000000", "followers_count": 814, "profile_sidebar_border_color": "000000", "id_str": "725791584910888961", "profile_background_color": "000000", "listed_count": 1, "profile_background_image_url_https": "https://abs.twimg.com/images/themes/theme1/bg.png", "utc_offset": null, "statuses_count": 6491, "description": "If you'll unfollow, don't bother following. Am sorry, am not as funny as you thought!\n\n\u300aI follow back\u300b\n\nhttps://t.co/Yo7CK0w6q1\nhttps://t.co/M7rLbRqS4L", "friends_count": 1379, "location": "Happiness ", "profile_link_color": "1B95E0", "profile_image_url": "http://pbs.twimg.com/profile_images/1031132166036631552/Yewxcyqo_normal.jpg", "following": null, "geo_enabled": true, "profile_banner_url": "https://pbs.twimg.com/profile_banners/725791584910888961/1512753773", "profile_background_image_url": "http://abs.twimg.com/images/themes/theme1/bg.png", "name": "The incorruptible seed", "lang": null, "profile_background_tile": false, "favourites_count": 4717, "screen_name": "jnkomaho", "notifications": null, "url": null, "created_at": "Thu Apr 28 20:59:33 +0000 2016", "contributors_enabled": false, "time_zone": null, "protected": false, "translator_type": "none", "is_translator": false}, "geo": null, "in_reply_to_user_id_str": "437573692", "lang": "en", "extended_tweet": {"display_text_range": [16, 163], "entities": {"user_mentions": [{"id": 437573692, "indices": [0, 15], "id_str": "437573692", "screen_name": "CarolNatukunda", "name": "Carol Natukunda"}], "symbols": [], "hashtags": [], "urls": []}, "full_text": "@CarolNatukunda Ohh God!!\nThat's why they use HS codes. Tax collectors may not know all the products but they'll know which category they belong too hence HS code."}, "created_at": "Thu May 30 14:33:49 +0000 2019", "filter_level": "low", "in_reply_to_status_id_str": "1134104996881063938", "place": {"full_name": "Kampala, Uganda", "url": "https://api.twitter.com/1.1/geo/id/000c69ad123213a8.json", "country": "Uganda", "place_type": "admin", "bounding_box": {"type": "Polygon", "coordinates": [[[32.416623, 0.164853], [32.416623, 0.413682], [32.721697, 0.413682], [32.721697, 0.164853]]]}, "country_code": "UG", "attributes": {}, "id": "000c69ad123213a8", "name": "Kampala"}}
{"quote_count": 0, "contributors": null, "truncated": false, "text": "Going in style", "is_quote_status": false, "in_reply_to_status_id": null, "reply_count": 0, "id": 1134105658436046849, "favorite_count": 0, "source": "<a href=\"http://twitter.com\" rel=\"nofollow\">Twitter Web Client</a>", "retweeted": false, "coordinates": null, "timestamp_ms": "1559226834292", "entities": {"user_mentions": [], "symbols": [], "hashtags": [], "urls": []}, "in_reply_to_screen_name": null, "id_str": "1134105658436046849", "retweet_count": 0, "in_reply_to_user_id": null, "favorited": false, "user": {"follow_request_sent": null, "profile_use_background_image": true, "default_profile_image": false, "id": 242344900, "default_profile": false, "verified": false, "profile_image_url_https": "https://pbs.twimg.com/profile_images/1123873687965458435/QCj_nX-j_normal.jpg", "profile_sidebar_fill_color": "EFEFEF", "profile_text_color": "333333", "followers_count": 3622, "profile_sidebar_border_color": "000000", "id_str": "242344900", "profile_background_color": "131516", "listed_count": 26, "profile_background_image_url_https": "https://abs.twimg.com/images/themes/theme14/bg.gif", "utc_offset": null, "statuses_count": 61391, "description": "A lover of people, helper and talker (a noise maker). Interest-Music,Finance, movies, Digital stuff and Cakes.", "friends_count": 710, "location": "Kampala, Uganda", "profile_link_color": "1B95E0", "profile_image_url": "http://pbs.twimg.com/profile_images/1123873687965458435/QCj_nX-j_normal.jpg", "following": null, "geo_enabled": true, "profile_banner_url": "https://pbs.twimg.com/profile_banners/242344900/1512286470", "profile_background_image_url": "http://abs.twimg.com/images/themes/theme14/bg.gif", "name": "Reagan W. Mbabali", "lang": null, "profile_background_tile": true, "favourites_count": 6983, "screen_name": "Snipet7", "notifications": null, "url": "http://reagansnipet7.wordpress.com", "created_at": "Mon Jan 24 15:28:54 +0000 2011", "contributors_enabled": false, "time_zone": null, "protected": false, "translator_type": "none", "is_translator": false}, "geo": null, "in_reply_to_user_id_str": null, "lang": "en", "created_at": "Thu May 30 14:33:54 +0000 2019", "filter_level": "low", "in_reply_to_status_id_str": null, "place": {"full_name": "Uganda", "url": "https://api.twitter.com/1.1/geo/id/939067979a7f3b95.json", "country": "Uganda", "place_type": "country", "bounding_box": {"type": "Polygon", "coordinates": [[[29.573568, -1.481289], [29.573568, 4.23164], [35.03605, 4.23164], [35.03605, -1.481289]]]}, "country_code": "UG", "attributes": {}, "id": "939067979a7f3b95", "name": "Uganda"}}
{"quote_count": 0, "contributors": null, "truncated": false, "text": "@QuteJR It kills them to retweet a tweet with a # tag promoting something. Witches \ud83d\ude02\ud83d\ude02\ud83d\ude02\ud83d\ude02\ud83d\ude02\ud83d\ude02", "is_quote_status": false, "in_reply_to_status_id": 1134105315748790273, "reply_count": 0, "id": 1134105662848471040, "favorite_count": 0, "entities": {"user_mentions": [{"id": 1346118158, "indices": [0, 7], "id_str": "1346118158", "screen_name": "QuteJR", "name": "J\u00f8n ry\u00e1ns\u2122"}], "symbols": [], "hashtags": [], "urls": []}, "retweeted": false, "coordinates": null, "timestamp_ms": "1559226835344", "source": "<a href=\"http://twitter.com/download/android\" rel=\"nofollow\">Twitter for Android</a>", "in_reply_to_screen_name": "QuteJR", "id_str": "1134105662848471040", "display_text_range": [8, 89], "retweet_count": 0, "in_reply_to_user_id": 1346118158, "favorited": false, "user": {"follow_request_sent": null, "profile_use_background_image": true, "default_profile_image": false, "id": 935958230525730816, "default_profile": true, "verified": false, "profile_image_url_https": "https://pbs.twimg.com/profile_images/1133778032538341383/mFn1AhZF_normal.jpg", "profile_sidebar_fill_color": "DDEEF6", "profile_text_color": "333333", "followers_count": 11181, "profile_sidebar_border_color": "C0DEED", "id_str": "935958230525730816", "profile_background_color": "F5F8FA", "listed_count": 3, "profile_background_image_url_https": "", "utc_offset": null, "statuses_count": 151109, "description": "Real Madrid Club De F\u00fatbol \u2022 BMW \u2022 House Targaryen \u2022 The life I need is a little distant \u2022 #JubilewoCup110k \u2022 #Rockets", "friends_count": 11557, "location": "Wakiso, Uganda", "profile_link_color": "1DA1F2", "profile_image_url": "http://pbs.twimg.com/profile_images/1133778032538341383/mFn1AhZF_normal.jpg", "following": null, "geo_enabled": true, "profile_banner_url": "https://pbs.twimg.com/profile_banners/935958230525730816/1557946540", "profile_background_image_url": "", "name": "juli\u00f8 ( \u6731\u5229\u53f6\u65af )", "lang": null, "profile_background_tile": false, "favourites_count": 130468, "screen_name": "baketerana", "notifications": null, "url": "https://youtu.be/PL1r7zujSrk", "created_at": "Wed Nov 29 19:46:46 +0000 2017", "contributors_enabled": false, "time_zone": null, "protected": false, "translator_type": "none", "is_translator": false}, "geo": null, "in_reply_to_user_id_str": "1346118158", "lang": "en", "created_at": "Thu May 30 14:33:55 +0000 2019", "filter_level": "low", "in_reply_to_status_id_str": "1134105315748790273", "place": {"full_name": "Kampala, Uganda", "url": "https://api.twitter.com/1.1/geo/id/000c69ad123213a8.json", "country": "Uganda", "place_type": "admin", "bounding_box": {"type": "Polygon", "coordinates": [[[32.416623, 0.164853], [32.416623, 0.413682], [32.721697, 0.413682], [32.721697, 0.164853]]]}, "country_code": "UG", "attributes": {}, "id": "000c69ad123213a8", "name": "Kampala"}}
{"quote_count": 0, "contributors": null, "truncated": false, "text": "@dviola56 @Jude_Mugabi Wano yewa? I need some goat barbecue", "is_quote_status": false, "in_reply_to_status_id": 1134078498329563137, "reply_count": 0, "id": 1134106022824620033, "favorite_count": 0, "entities": {"user_mentions": [{"id": 504200364, "indices": [0, 9], "id_str": "504200364", "screen_name": "dviola56", "name": "Diana Violet"}, {"id": 712676897, "indices": [10, 22], "id_str": "712676897", "screen_name": "Jude_Mugabi", "name": "Usual Suspect"}], "symbols": [], "hashtags": [], "urls": []}, "retweeted": false, "coordinates": null, "timestamp_ms": "1559226921169", "source": "<a href=\"http://twitter.com/download/iphone\" rel=\"nofollow\">Twitter for iPhone</a>", "in_reply_to_screen_name": "dviola56", "id_str": "1134106022824620033", "display_text_range": [23, 59], "retweet_count": 0, "in_reply_to_user_id": 504200364, "favorited": false, "user": {"follow_request_sent": null, "profile_use_background_image": true, "default_profile_image": false, "id": 2470590086, "default_profile": true, "verified": false, "profile_image_url_https": "https://pbs.twimg.com/profile_images/1031981799726088197/Ny2cUBJS_normal.jpg", "profile_sidebar_fill_color": "DDEEF6", "profile_text_color": "333333", "followers_count": 2934, "profile_sidebar_border_color": "C0DEED", "id_str": "2470590086", "profile_background_color": "C0DEED", "listed_count": 27, "profile_background_image_url_https": "https://abs.twimg.com/images/themes/theme1/bg.png", "utc_offset": null, "statuses_count": 65560, "description": "Tribal/Deep House & Reggae lover : ______________________________________________For all your Moving Errands (Office, home, etc), kindly Dm.", "friends_count": 970, "location": "Kampala, Uganda", "profile_link_color": "1DA1F2", "profile_image_url": "http://pbs.twimg.com/profile_images/1031981799726088197/Ny2cUBJS_normal.jpg", "following": null, "geo_enabled": true, "profile_banner_url": "https://pbs.twimg.com/profile_banners/2470590086/1558723073", "profile_background_image_url": "http://abs.twimg.com/images/themes/theme1/bg.png", "name": "Mr. B\u00e1ldi\u00e9 R\u00e9nz\u00e9l", "lang": null, "profile_background_tile": false, "favourites_count": 37970, "screen_name": "Kamali_21", "notifications": null, "url": "http://www.quickerrands.com", "created_at": "Wed Apr 30 09:15:11 +0000 2014", "contributors_enabled": false, "time_zone": null, "protected": false, "translator_type": "none", "is_translator": false}, "geo": null, "in_reply_to_user_id_str": "504200364", "lang": "en", "created_at": "Thu May 30 14:35:21 +0000 2019", "filter_level": "low", "in_reply_to_status_id_str": "1134078498329563137", "place": {"full_name": "Wakiso, Uganda", "url": "https://api.twitter.com/1.1/geo/id/0092409a629e836c.json", "country": "Uganda", "place_type": "admin", "bounding_box": {"type": "Polygon", "coordinates": [[[32.192297, -0.147789], [32.192297, 0.585072], [32.683699, 0.585072], [32.683699, -0.147789]]]}, "country_code": "UG", "attributes": {}, "id": "0092409a629e836c", "name": "Wakiso"}}
{"quote_count": 0, "contributors": null, "truncated": false, "text": "The Clock is Ticking Anti-clockwise\ud83d\udc51\nI know you see the wave\ud83c\udf0a coming\n\n@mixkillerdj2 \ud83d\udcbd\n#WULILAEBAALA https://t.co/a28Ka7SuSA", "is_quote_status": false, "in_reply_to_status_id": null, "reply_count": 0, "id": 1134106043192086528, "favorite_count": 0, "entities": {"user_mentions": [{"id": 947871936612372481, "indices": [70, 83], "id_str": "947871936612372481", "screen_name": "mixkillerdj2", "name": "Dj aron de mixkiller"}], "symbols": [], "hashtags": [{"indices": [86, 99], "text": "WULILAEBAALA"}], "urls": [], "media": [{"expanded_url": "https://twitter.com/phic_wills/status/1134106043192086528/photo/1", "display_url": "pic.twitter.com/a28Ka7SuSA", "url": "https://t.co/a28Ka7SuSA", "media_url_https": "https://pbs.twimg.com/media/D70natVWwAAm_gC.jpg", "id_str": "1134106020966481920", "sizes": {"large": {"h": 764, "resize": "fit", "w": 764}, "small": {"h": 680, "resize": "fit", "w": 680}, "medium": {"h": 764, "resize": "fit", "w": 764}, "thumb": {"h": 150, "resize": "crop", "w": 150}}, "indices": [100, 123], "type": "photo", "id": 1134106020966481920, "media_url": "http://pbs.twimg.com/media/D70natVWwAAm_gC.jpg"}]}, "retweeted": false, "coordinates": null, "timestamp_ms": "1559226926025", "source": "<a href=\"http://twitter.com/download/android\" rel=\"nofollow\">Twitter for Android</a>", "in_reply_to_screen_name": null, "id_str": "1134106043192086528", "display_text_range": [0, 99], "retweet_count": 0, "in_reply_to_user_id": null, "favorited": false, "user": {"follow_request_sent": null, "profile_use_background_image": true, "default_profile_image": false, "id": 801814233935540224, "default_profile": true, "verified": false, "profile_image_url_https": "https://pbs.twimg.com/profile_images/1131613384598798337/Zvhv0tQE_normal.jpg", "profile_sidebar_fill_color": "DDEEF6", "profile_text_color": "333333", "followers_count": 149, "profile_sidebar_border_color": "C0DEED", "id_str": "801814233935540224", "profile_background_color": "F5F8FA", "listed_count": 1, "profile_background_image_url_https": "", "utc_offset": null, "statuses_count": 384, "description": "The Only Banger\ud83d\udd25\ud83d\udc83 Yo Favourite  Deejay\ud83d\udcbd Needs to correct his sound\ud83c\udfa7\ud83d\udce2\ud83d\ude02 #Wulilaebaala Download\ud83d\udc47", "friends_count": 190, "location": "Africa", "profile_link_color": "1DA1F2", "profile_image_url": "http://pbs.twimg.com/profile_images/1131613384598798337/Zvhv0tQE_normal.jpg", "following": null, "geo_enabled": true, "profile_banner_url": "https://pbs.twimg.com/profile_banners/801814233935540224/1551607809", "profile_background_image_url": "", "name": "Phic Wills", "lang": null, "profile_background_tile": false, "favourites_count": 829, "screen_name": "phic_wills", "notifications": null, "url": "https://mdundo.com/song/1305386", "created_at": "Thu Nov 24 15:46:25 +0000 2016", "contributors_enabled": false, "time_zone": null, "protected": false, "translator_type": "none", "is_translator": false}, "geo": null, "in_reply_to_user_id_str": null, "possibly_sensitive": false, "lang": "en", "created_at": "Thu May 30 14:35:26 +0000 2019", "filter_level": "low", "in_reply_to_status_id_str": null, "place": {"full_name": "Kampala, Uganda", "url": "https://api.twitter.com/1.1/geo/id/000c69ad123213a8.json", "country": "Uganda", "place_type": "admin", "bounding_box": {"type": "Polygon", "coordinates": [[[32.416623, 0.164853], [32.416623, 0.413682], [32.721697, 0.413682], [32.721697, 0.164853]]]}, "country_code": "UG", "attributes": {}, "id": "000c69ad123213a8", "name": "Kampala"}, "extended_entities": {"media": [{"expanded_url": "https://twitter.com/phic_wills/status/1134106043192086528/photo/1", "display_url": "pic.twitter.com/a28Ka7SuSA", "url": "https://t.co/a28Ka7SuSA", "media_url_https": "https://pbs.twimg.com/media/D70natVWwAAm_gC.jpg", "id_str": "1134106020966481920", "sizes": {"large": {"h": 764, "resize": "fit", "w": 764}, "small": {"h": 680, "resize": "fit", "w": 680}, "medium": {"h": 764, "resize": "fit", "w": 764}, "thumb": {"h": 150, "resize": "crop", "w": 150}}, "indices": [100, 123], "type": "photo", "id": 1134106020966481920, "media_url": "http://pbs.twimg.com/media/D70natVWwAAm_gC.jpg"}]}}
{"quote_count": 0, "contributors": null, "truncated": false, "text": "@Phil_Okumu @DorcusMagoba Heard of overkill or over regulation? What purpose would that rule serve?", "is_quote_status": false, "in_reply_to_status_id": 1134028774079680512, "reply_count": 0, "id": 1134106282460418049, "favorite_count": 0, "entities": {"user_mentions": [{"id": 188254953, "indices": [0, 11], "id_str": "188254953", "screen_name": "Phil_Okumu", "name": "Philip Okumu"}, {"id": 373373482, "indices": [12, 25], "id_str": "373373482", "screen_name": "DorcusMagoba", "name": "Dorcus Magoba"}], "symbols": [], "hashtags": [], "urls": []}, "retweeted": false, "coordinates": null, "timestamp_ms": "1559226983071", "source": "<a href=\"http://twitter.com/download/android\" rel=\"nofollow\">Twitter for Android</a>", "in_reply_to_screen_name": "Phil_Okumu", "id_str": "1134106282460418049", "display_text_range": [26, 99], "retweet_count": 0, "in_reply_to_user_id": 188254953, "favorited": false, "user": {"follow_request_sent": null, "profile_use_background_image": true, "default_profile_image": false, "id": 1118555838, "default_profile": true, "verified": false, "profile_image_url_https": "https://pbs.twimg.com/profile_images/1107320255775494144/T9PBC-eB_normal.jpg", "profile_sidebar_fill_color": "DDEEF6", "profile_text_color": "333333", "followers_count": 1692, "profile_sidebar_border_color": "C0DEED", "id_str": "1118555838", "profile_background_color": "C0DEED", "listed_count": 9, "profile_background_image_url_https": "https://abs.twimg.com/images/themes/theme1/bg.png", "utc_offset": null, "statuses_count": 2812, "description": "CTP, CHRBP, FAAPM, BSP, Brother, Son, Father, Husband, Crazy about eLearning, Basketball, Fitness, Eq